{"cAwP7nmFpntnf38YIdbMtA==":"215323fvkzdmgdvryyynhz.png","OcOFR9Jk2YdZWXNLw7smWg==":"rezero.jpg","t0wGneSxmZLp422d1JMQyw==":"00381582.jpg","ZLYRPgUChI3tRahqvX7USw==":"-lost-in-memories.jpg","LiZAiTtW8kNJt3exkkFGQw==":"ao4fymhasqv4kx3a5h850ks9vfhx6nc.png","Yu3GosYqSSN51U9ko1UaWw==":"-lost-in-memories.jpeg","pwI5FWIT79nqq3AJFLy3yg==":"nbnaum3xxijn2czm4etowmzm1utm1qdn5mjm5admwajmwuzlxkzlzazlt92yucmbvrwdo5cd0fmlwe2lvodc0rha.jpg","hRfgZkn6VJ57JL6StEaMtQ==":"-.jpg","GF5R9et0i4yQszubLcygKA==":"1.jpg","bg+BPmPODL83hj3Qz2u9SQ==":"unnamed.png","JIj2S0WatoNgA4Jdwzfgvg==":"830a63ce06.jpg","d3H1m3bCoihGcPygTB3ABg==":"2.png","r3mgjOCEIa6BNmpg6UrbpQ==":"4.png","ZrDQGTpquAQUeIaSXeu1rQ==":"5.png","rPDUIEYgRY/4jrWP7J+cSw==":"3.png","HW4N95rntSuV5FUQKvg7wg==":"6.png","G3tFw3vx7rarhO1jRYFhbA==":"1-200z3131g3p0.jpg","m00RXfTMK7atqTmhW6F7YA==":"u4568227143416207515fm173app49fjpeg.jpg","29eIRuwLRVw887tYTOpsow==":"-1.jpg","XvUI7X9RZnUE7dq3PMdTdw==":"murakawa-3.jpg","TDeFvKgJqRwf0zkh9aWckw==":"d16356-2496-382216.jpg","inL27dF57xkLIL5Dwm6JKA==":"350px-.jpg","QklSzzFYcX5uhN47Q1gmuA==":"84fa308a4758df9375aa4a4c99157pw5.jpg","JDJMqrCSMZ9UnSKitmQ68Q==":"w1200.jpg","mlvsMiYcXUCXMCPzoKvyhw==":"w1200-1.jpg","nACIki2nflj3k7dFlKEN+Q==":"w1200-2.jpg","7Sl/shQnOpjZ3mzlQBEHTg==":"w1200-3.jpg","pUD/VsQ6tvDZcDRnO6R7tA==":"w1200-4.jpg","GRA6Leylqyk5FAtr5ssooQ==":"w1200-5.jpg","DHNjg4P6OlX27FQK3dxSCg==":"w1200-6.jpg","teZNgc07mdGM+locheBSeg==":"w1200-7.jpg","0xUkyvQVbMw1srwQ/qECEw==":"w1200-8.jpg"}